cloninator/__init__.py
cloninator/__main__.py
cloninator/__version__.py
cloninator/clone.py
cloninator/generate.py
cloninator/utils.py
cloninator-0.1.0.dist-info/METADATA
cloninator-0.1.0.dist-info/WHEEL
cloninator-0.1.0.dist-info/entry_points.txt
cloninator-0.1.0.dist-info/RECORD
