Metadata-Version: 2.1
Name: cloninator
Version: 0.1.0
Summary: A cli tool to clone your repos
Home-page: https://cloninator.readthedocs.io/en/stable/
License: LGPL-3.0+
Keywords: git
Author: Stephanos Kuma
Author-email: stephanos@kuma.ai
Requires-Python: >=3.11,<4.0
Classifier: Development Status :: 3 - Alpha
Classifier: License :: OSI Approved :: GNU Lesser General Public License v3 or later (LGPLv3+)
Classifier: Operating System :: OS Independent
Classifier: Programming Language :: Python :: 3
Classifier: Programming Language :: Python :: 3.11
Classifier: Programming Language :: Python :: 3.12
Requires-Dist: PyYAML (>=6.0,<7.0)
Requires-Dist: dj_settings (>=5.0,<6.0)
Project-URL: Documentation, https://cloninator.readthedocs.io/en/stable/
Project-URL: Repository, https://github.com/spapanik/cloninator
